just_driver/__init__.py
just_driver/client.py
just_driver/log.py
just_driver/api/__init__.py
just_driver/api/connection.py
just_driver/api/cursor.py
just_driver/api/errors.py
just_driver/api/service.py
just_driver/config/__init__.py
just_driver/config/connection_config.py
just_driver/config/connection_sync_config.py
just_driver/constant/__init__.py
just_driver/constant/builtin_config_enum.py
just_driver/constant/error_response_enum.py
just_driver/constant/request_enum.py
just_driver/constant/type_enum.py
just_driver/util/__init__.py
just_driver/util/str_util.py
just_driver_python-2.1.2.dist-info/METADATA
just_driver_python-2.1.2.dist-info/WHEEL
just_driver_python-2.1.2.dist-info/top_level.txt
just_driver_python-2.1.2.dist-info/RECORD
